Workbook

Sheet Source_Data
A1: ICICI Bank Financial Performance Analysis — Source Data
A2: Source: ICICI Bank official performance review for quarter ended June 30, 2026 (Q1 FY2027)
A3: Amounts are ₹ crore unless the metric is a percentage. Income figures are for a quarter; deposits/advances are period-end balances.
A4: Metric | B4: Unit | C4: Q1 FY2026 | D4: Q4 FY2026 | E4: Q1 FY2027 | F4: Metric Type
A5: Net interest income (NII) | B5: ₹ crore | C5: 21635 | D5: 22979 | E5: 24384 | F5: Quarterly income
A6: Profit after tax (PAT) | B6: ₹ crore | C6: 12768 | D6: 13702 | E6: 14805 | F6: Quarterly income
A7: Operating expenses | B7: ₹ crore | C7: 11394 | D7: 12089 | E7: 12574 | F7: Quarterly income
A8: Core operating profit | B8: ₹ crore | C8: 17505 | D8: 18305 | E8: 20235 | F8: Quarterly income
A9: Net interest margin (NIM) | B9: % | C9: 4.34 | D9: 4.32 | E9: 4.36 | F9: Ratio
A10: Deposits | B10: ₹ crore | C10: 1608517 | D10: 1794625 | E10: 1833586 | F10: Period-end balance
A11: Advances / loan portfolio | B11: ₹ crore | C11: 1364157 | D11: 1553893 | E11: 1631260 | F11: Period-end balance
A12: Gross NPA ratio | B12: % | C12: 1.67 | D12: 1.4 | E12: 1.38 | F12: Period-end ratio
A13: Net NPA ratio | B13: % | C13: 0.41 | D13: 0.33 | E13: 0.35 | F13: Period-end ratio
A14: Total capital adequacy ratio | B14: % | E14: 16.84 | F14: Period-end ratio
A15: Fee income | B15: ₹ crore | C15: 5900 | D15: 6779 | E15: 7286 | F15: Quarterly income
A16: Provisions (excluding tax) | B16: ₹ crore | C16: 1815 | D16: 96 | E16: 1260 | F16: Quarterly expense

Sheet Analysis
A1: Analysis — Calculate Growth and Changes
A2: Growth = (current period / prior period) - 1. Ratio change = current ratio minus prior ratio.
A3: Metric | B3: Q1 FY2026 | C3: Q4 FY2026 | D3: Q1 FY2027 | E3: Year-on-year change
A4: =Source_Data!A5 | B4: =Source_Data!C5 | C4: =Source_Data!D5 | D4: =Source_Data!E5 | E4: =IFERROR(D4/B4-1,"")
A5: =Source_Data!A6 | B5: =Source_Data!C6 | C5: =Source_Data!D6 | D5: =Source_Data!E6 | E5: =IFERROR(D5/B5-1,"")
A6: =Source_Data!A7 | B6: =Source_Data!C7 | C6: =Source_Data!D7 | D6: =Source_Data!E7 | E6: =IFERROR(D6/B6-1,"")
A7: =Source_Data!A8 | B7: =Source_Data!C8 | C7: =Source_Data!D8 | D7: =Source_Data!E8 | E7: =IFERROR(D7/B7-1,"")
A8: =Source_Data!A9 | B8: =Source_Data!C9 | C8: =Source_Data!D9 | D8: =Source_Data!E9 | E8: =IFERROR(D8-B8,"")
A9: =Source_Data!A10 | B9: =Source_Data!C10 | C9: =Source_Data!D10 | D9: =Source_Data!E10 | E9: =IFERROR(D9/B9-1,"")
A10: =Source_Data!A11 | B10: =Source_Data!C11 | C10: =Source_Data!D11 | D10: =Source_Data!E11 | E10: =IFERROR(D10/B10-1,"")
A11: =Source_Data!A12 | B11: =Source_Data!C12 | C11: =Source_Data!D12 | D11: =Source_Data!E12 | E11: =IFERROR(D11-B11,"")
A12: =Source_Data!A13 | B12: =Source_Data!C13 | C12: =Source_Data!D13 | D12: =Source_Data!E13 | E12: =IFERROR(D12-B12,"")
A13: =Source_Data!A14 | B13: =Source_Data!C14 | C13: =Source_Data!D14 | D13: =Source_Data!E14 | E13: =IFERROR(D13-B13,"")
A14: =Source_Data!A15 | B14: =Source_Data!C15 | C14: =Source_Data!D15 | D14: =Source_Data!E15 | E14: =IFERROR(D14/B14-1,"")
A15: =Source_Data!A16 | B15: =Source_Data!C16 | C15: =Source_Data!D16 | D15: =Source_Data!E16 | E15: =IFERROR(D15/B15-1,"")
A18: Interpretation note
A19: Compare quarterly income with the same quarter one year earlier for YoY analysis. Deposits and advances are period-end balances. For ratios, explain the change in percentage points.

Sheet Glossary
A1: Beginner Glossary
A2: Term | B2: Simple meaning | C2: Why it matters
A3: NII | B3: Interest earned minus interest paid on deposits and borrowings. | C3: A core source of a bank's income.
A4: PAT | B4: Profit after tax. | C4: Shows the profit remaining after tax for the period.
A5: NIM | B5: Net interest income relative to average interest-earning assets, expressed as a percentage. | C5: Helps assess interest-related earning performance.
A6: Deposits | B6: Money customers place with a bank. | C6: A key source of funding for a bank.
A7: Advances | B7: Loans and credit provided by the bank. | C7: Shows lending activity; growth must be considered alongside risk.
A8: Gross NPA ratio | B8: Share of loans classified as non-performing before relevant provisions. | C8: An indicator of asset quality.
A9: Net NPA ratio | B9: Ratio of net non-performing assets after relevant provisions. | C9: Another indicator of asset quality.
A10: Capital adequacy ratio | B10: Regulatory capital relative to risk-weighted assets. | C10: Indicates the bank's capital buffer against risk.
A11: YoY | B11: Year-on-year: compared with the same quarter one year earlier. | C11: Helps make a like-for-like comparison.
A12: Percentage point | B12: Arithmetic difference between two percentages. | C12: 4.34% to 4.36% is +0.02 percentage points.
